[{"stackHeaders":{"api_key":"blt3d61a480ac6e0604","authorization":"cs9cd5b309c21921ad270b878e"},"urlPath":"/assets/blte507cd0d326445fe","uid":"blte507cd0d326445fe","content_type":"image/png","file_size":"280253","tags":[],"filename":"ea-softball.png","url":"https://images.contentstack.io/v3/assets/blt3d61a480ac6e0604/blte507cd0d326445fe/613bb13812a5a65600befd75/ea-softball.png","ACL":{},"is_dir":false,"parent_uid":"blte365adc08f11178c","_version":1,"title":"ea-softball.png","publish_details":[{"environment":"blt79ff16810a0e20ee","locale":"en-us","time":"2021-09-10T19:25:45.263Z","user":"blt4c4e5e098d228a12","version":1}]}]